sloth_ci/ext/robots.txt
sloth_ci/ext/robots_txt.py
sloth_ci.ext.robots_txt-1.0.3.dist-info/DESCRIPTION.rst
sloth_ci.ext.robots_txt-1.0.3.dist-info/METADATA
sloth_ci.ext.robots_txt-1.0.3.dist-info/RECORD
sloth_ci.ext.robots_txt-1.0.3.dist-info/WHEEL
sloth_ci.ext.robots_txt-1.0.3.dist-info/metadata.json
sloth_ci.ext.robots_txt-1.0.3.dist-info/top_level.txt
