Metadata-Version: 2.0
Name: sloth-ci.ext.robots-txt
Version: 1.0.3
Summary: Robots.txt for the Sloth CI server
Home-page: https://bitbucket.org/moigagoo/sloth-ci-extensions
Author: Konstantin Molchanov
Author-email: moigagoo@live.com
License: MIT
Platform: UNKNOWN
Classifier: Development Status :: 5 - Production/Stable
Classifier: Intended Audience :: Developers
Classifier: Natural Language :: English
Classifier: Programming Language :: Python
Classifier: Programming Language :: Python :: 3
Requires-Dist: sloth-ci (>=2.0.1)
